README.md
setup.py
gandb/Binomialdistribution.py
gandb/Gaussiandistribution.py
gandb/Generaldistribution.py
gandb/__init__.py
gandb.egg-info/PKG-INFO
gandb.egg-info/SOURCES.txt
gandb.egg-info/dependency_links.txt
gandb.egg-info/not-zip-safe
gandb.egg-info/top_level.txt